lib_database/__init__.py
lib_database/database.py
lib_database/generic_table.py
lib_database/tests/__init__.py
lib_database/tests/conftest.py
lib_database/tests/test_database.py
lib_database/tests/test_generic_table.py
lib_database-0.0.1.dist-info/AUTHORS
lib_database-0.0.1.dist-info/LICENSE
lib_database-0.0.1.dist-info/METADATA
lib_database-0.0.1.dist-info/WHEEL
lib_database-0.0.1.dist-info/entry_points.txt
lib_database-0.0.1.dist-info/top_level.txt
lib_database-0.0.1.dist-info/RECORD
