Metadata-Version: 2.1
Name: lib-database
Version: 0.0.1
Summary: Wrapper around a postgres database
Home-page: https://github.com/jfuruness/lib_database.git
Author: Justin Furuness
Author-email: jfuruness@gmail.com
Maintainer: Justin Furuness
Maintainer-email: jfuruness@gmail.com
License: UNKNOWN
Download-URL: https://github.com/jfuruness/lib_database.git
Platform: UNKNOWN
Classifier: Environment :: Console
Classifier: Environment :: Web Environment
Classifier: Intended Audience :: Developers
Classifier: Operating System :: POSIX :: Linux
Classifier: Programming Language :: Python :: 3
Requires-Python: >=3.8
Requires-Dist: numpy
Requires-Dist: psycopg2-binary
Requires-Dist: pytest
